reachab/__init__.py
reachab/__main__.py
reachab/src/__init__.py
reachab/src/reachability.py
reachab/src/states_reachsets.py
reachab/util/__init__.py
reachab/util/util_functions.py
reachab/util/visualizer.py
reachab-0.4.17.dist-info/METADATA
reachab-0.4.17.dist-info/WHEEL
reachab-0.4.17.dist-info/top_level.txt
reachab-0.4.17.dist-info/RECORD
