Metadata-Version: 2.1
Name: reachab
Version: 0.4.17
Summary: Reachability Analysis with zonotypes
Home-page: https://github.com/ga74kud/reachab
Author: Michael Hartmann
Author-email: michael.hartmann@v2c2.at
License: GNU GENERAL PUBLIC LICENSE
Platform: UNKNOWN
Requires-Dist: scipy
Requires-Dist: numpy
Requires-Dist: matplotlib
Requires-Dist: argparse
Requires-Dist: shapely
